nadi/__init__.py
nadi/nadi.cpython-312-darwin.so
nadi_py-0.7.2.dist-info/METADATA
nadi_py-0.7.2.dist-info/WHEEL
nadi_py-0.7.2.dist-info/licenses/LICENSE
nadi_py-0.7.2.dist-info/RECORD
