Metadata-Version: 2.4
Name: nadi-py
Version: 0.7.2
Classifier: Programming Language :: Rust
Classifier: Programming Language :: Python :: Implementation :: CPython
Classifier: Programming Language :: Python :: Implementation :: PyPy
Classifier: Development Status :: 4 - Beta
Classifier: License :: OSI Approved :: GNU General Public License v3 (GPLv3)
Classifier: Topic :: Scientific/Engineering :: Hydrology
License-File: LICENSE
Summary: Python bindings to the Network Analysis and Data Integration (NADI) System
Keywords: river,hydrology,network analysis,environmental modeling
Requires-Python: >=3.8
Project-URL: homepage, https://nadi-system.github.io/
Project-URL: documentation, https://nadi-system.github.io/python.html
Project-URL: repository, https://github.com/Nadi-System/nadi-system
